commitcraft/CommitCraft.py
commitcraft/__init__.py
commitcraft/__main__.py
commitcraft/config_handler.py
commitcraft/defaults.py
commitcraft-1.0.0.dist-info/METADATA
commitcraft-1.0.0.dist-info/WHEEL
commitcraft-1.0.0.dist-info/entry_points.txt
commitcraft-1.0.0.dist-info/licenses/LICENSE
commitcraft-1.0.0.dist-info/RECORD
