Metadata-Version: 2.4
Name: commitcraft
Version: 1.0.0
Summary: A simple tool to use LLM and git diff to craft meaningfull commit messages.
License: AGPL-3.0
License-File: LICENSE
Keywords: llm,commit,ai,openai,ollama,groq,git,dev,commit messages
Author: Felix-Pedro
Author-email: felix@auneria.com
Requires-Python: >=3.10,<4.0
Classifier: License :: OSI Approved :: GNU Affero General Public License v3
Classifier: Programming Language :: Python :: 3
Classifier: Programming Language :: Python :: 3.10
Classifier: Programming Language :: Python :: 3.11
Classifier: Programming Language :: Python :: 3.12
Classifier: Programming Language :: Python :: 3.13
Classifier: Programming Language :: Python :: 3.14
Classifier: Topic :: Software Development :: Version Control :: Git
Classifier: Topic :: Utilities
Provides-Extra: all-providers
Provides-Extra: google
Provides-Extra: groq
Provides-Extra: openai
Requires-Dist: click (>=8.1.0,<8.2.0)
Requires-Dist: google-genai (>=0.2.0,<0.3.0) ; extra == "google" or extra == "all-providers"
Requires-Dist: groq (>=0.11.0,<0.12.0) ; extra == "groq" or extra == "all-providers"
Requires-Dist: h11 (>=0.16.0,<0.17.0)
Requires-Dist: jinja2 (>=3.1.6,<4.0.0)
Requires-Dist: ollama (>=0.3.3,<0.4.0)
Requires-Dist: openai (>=1.52.0,<2.0.0) ; extra == "openai" or extra == "all-providers"
Requires-Dist: pydantic (>=2.9.2,<3.0.0)
Requires-Dist: python-dotenv (>=1.0.1,<2.0.0)
Requires-Dist: pyyaml (>=6.0.2,<7.0.0)
Requires-Dist: requests (>=2.32.4,<3.0.0)
Requires-Dist: rich (>=14.2.0,<15.0.0)
Requires-Dist: toml (>=0.10.2,<0.11.0)
Requires-Dist: tomli (>=2.0.2,<3.0.0)
Requires-Dist: typer (>=0.12.5,<0.13.0)
Requires-Dist: urllib3 (>=2.6.0,<3.0.0)
Project-URL: Repository, https://github.com/Felix-Pedro/CommitCraft
